image_processing_thayse/__init__.py
image_processing_thayse/processing/__init__.py
image_processing_thayse/processing/combination.py
image_processing_thayse/processing/transformation.py
image_processing_thayse/utils/__init__.py
image_processing_thayse/utils/io.py
image_processing_thayse/utils/plot.py
image_processing_thayse-0.0.2.dist-info/METADATA
image_processing_thayse-0.0.2.dist-info/WHEEL
image_processing_thayse-0.0.2.dist-info/top_level.txt
image_processing_thayse-0.0.2.dist-info/RECORD
