Metadata-Version: 2.1
Name: image-processing-thayse
Version: 0.0.2
Summary: histrogram matching, structural similarity, resize image
Home-page: https://github.com/thaysetakamori/image-processing-package
Author: Thayse
Requires-Python: >=3.8
Requires-Dist: matplotlib
Requires-Dist: numpy
Requires-Dist: scikit-image>=0.16.1
